README.md
license
setup.py
lywt/FilePcocessing.py
lywt/__init__.py
lywt.egg-info/PKG-INFO
lywt.egg-info/SOURCES.txt
lywt.egg-info/dependency_links.txt
lywt.egg-info/top_level.txt
lywt/cli/__init__.py
lywt/cli/fileCut.py
lywt/cli/fileMD5.py
lywt/cli/musicEnjoy.py
lywt/cli/nobody.py
lywt/cli/pictureCompress.py
lywt/cli/textProcessing.py
lywt/gui/__init__.py
lywt/gui/fileMD5_gui.py